llm_classify/__init__.py
llm_classify/examples.py
llm_classify-0.1.2.dist-info/licenses/LICENSE
llm_classify-0.1.2.dist-info/METADATA
llm_classify-0.1.2.dist-info/WHEEL
llm_classify-0.1.2.dist-info/entry_points.txt
llm_classify-0.1.2.dist-info/top_level.txt
llm_classify-0.1.2.dist-info/RECORD
