Metadata-Version: 2.4
Name: llm-classify
Version: 0.1.2
Summary: LLM plugin for content classification using various language models
Author-email: Thomas Thomas Hughes <irthomasthomas@gmail.com>
License: Apache-2.0
Project-URL: Homepage, https://github.com/irthomasthomas/llm-classifier
Project-URL: Changelog, https://github.com/irthomasthomas/llm-classifier/releases
Project-URL: Issues, https://github.com/irthomasthomas/llm-classifier/issues
Classifier: License :: OSI Approved :: Apache Software License
License-File: LICENSE
Requires-Dist: llm
Requires-Dist: click
Dynamic: license-file
